Metadata-Version: 2.1
Name: upsty
Version: 1.0
Summary: Command line tool for up.psty.io
Home-page: https://github.com/psty-io/upsty
Author: Max Bridgland
Author-email: mabridgland@protonmail.com
License: GNU General Public License v3 (GPLv3) (GPL)
Project-URL: Wiki, https://github.com/psty-io/upsty/wiki
Project-URL: Discord Server, https://discord.gg/HphdfxU
Platform: UNKNOWN
Classifier: Development Status :: 4 - Beta
Classifier: Environment :: Console
Classifier: License :: OSI Approved :: GNU General Public License v3 (GPLv3)
Classifier: Programming Language :: Python
Classifier: Programming Language :: Python :: 3.6
Classifier: Programming Language :: Python :: 3.7
Classifier: Programming Language :: Python :: Implementation :: CPython
Classifier: Programming Language :: Python :: Implementation :: PyPy
Classifier: Programming Language :: Python :: Implementation :: IronPython
Classifier: Programming Language :: Python :: Implementation :: Jython
Classifier: Intended Audience :: Developers
Classifier: Intended Audience :: System Administrators
Classifier: Intended Audience :: Information Technology
Classifier: Topic :: Software Development :: Libraries :: Python Modules
Classifier: Topic :: Software Development :: Libraries
Classifier: Topic :: System :: Systems Administration
Classifier: Topic :: System :: Networking
Classifier: Topic :: Utilities
